{
  "parent": "prodigytech:recipes/root",
  "rewards": {
    "recipes": [
      "prodigytech:materials/circuit_plate_unfired"
    ]
  },
  "criteria": {
    "has_material": {
      "trigger": "minecraft:inventory_changed",
      "conditions": {
        "items": [
          {
            "item": "prodigytech:solderer"
          }
        ]
      }
    },
    "has_the_recipe": {
      "trigger": "minecraft:recipe_unlocked",
      "conditions": {
        "recipe": "prodigytech:materials/circuit_plate_unfired"
      }
    }
  },
  "requirements": [
    [
      "has_material",
      "has_the_recipe"
    ]
  ]
}